ciscopykit/__init__.py
ciscopykit/app.py
ciscopykit/device.py
ciscopykit/entry_point.py
ciscopykit/interface.py
ciscopykit/etherchannel/__init__.py
ciscopykit/etherchannel/cli.py
ciscopykit/etherchannel/etherchannel.py
ciscopykit/ip/__init__.py
ciscopykit/ip/vlsm.py
ciscopykit/routing/__init__.py
ciscopykit/routing/app.py
ciscopykit/routing/dynamic_routing.py
ciscopykit/routing/static_routing.py
ciscopykit/security/__init__.py
ciscopykit/security/acl/__init__.py
ciscopykit/security/acl/acl.py
ciscopykit/security/lan_security/__init__.py
ciscopykit/security/lan_security/app.py
ciscopykit/security/lan_security/dhcp_snooping.py
ciscopykit/security/lan_security/dynamic_arp_inspection.py
ciscopykit/security/lan_security/stp_security.py
ciscopykit/security/lan_security/switchport_security.py
ciscopykit/security/lan_security/vlan_security.py
ciscopykit/services/__init__.py
ciscopykit/services/app.py
ciscopykit/services/dhcp_service.py
ciscopykit/services/pat_service.py
ciscopykit/switch/__init__.py
ciscopykit/switch/app.py
ciscopykit/switch/l2_switch.py
ciscopykit/switch/l3_switch.py
ciscopykit/switch/switch.py
ciscopykit/vlan/__init__.py
ciscopykit/vlan/app.py
ciscopykit/vlan/vlan.py
ciscopykit-2.3.2.dist-info/LICENSE.md
ciscopykit-2.3.2.dist-info/METADATA
ciscopykit-2.3.2.dist-info/WHEEL
ciscopykit-2.3.2.dist-info/entry_points.txt
ciscopykit-2.3.2.dist-info/top_level.txt
ciscopykit-2.3.2.dist-info/RECORD
