Metadata-Version: 2.1
Name: ciscopykit
Version: 2.3.2
Summary: A network management toolkit for Cisco devices keeping track of devices when using GNS3 / Cisco Packet Tracer
Home-page: https://github.com/Vincent-de-Torres-Portfolio/ciscopykit
Author: devinci-it
Author-email: vince.dev@icloud.com
Classifier: Development Status :: 3 - Alpha
Classifier: Intended Audience :: Developers
Classifier: License :: OSI Approved :: MIT License
Classifier: Operating System :: OS Independent
Classifier: Programming Language :: Python :: 3
Classifier: Programming Language :: Python :: 3.8
Classifier: Programming Language :: Python :: 3.9
Classifier: Programming Language :: Python :: 3.11
License-File: LICENSE.md
Requires-Dist: click
Requires-Dist: networkx
Requires-Dist: matplotlib
Requires-Dist: ipaddress
Requires-Dist: argparse
